{
  "HOME": "Zuhause",
  "PREVIOUS": "Vor",
  "NOW": "Jetzt ",
  "NEXT": "Folgt",
  "STATIONS": "Kanäle",
  "RECENTLY": "Kürzlich gespielt",
  "SEE_ALL": "Alle ansehen",
  "RECENT_SONGS": "Aktuelle Lieder in",
  "PROFILE": "Profil",
  "SETTINGS": "Einstellungen",
  "WA_FEED": "WhatsApp-Feedback(Rückmeldung)",
  "ABOUT": "Über",
  "WA_ERR": "Stellen Sie sicher, dass Sie WhatsApp installiert haben",
  "PUSH_NOTIFICATIONS": "Notificări Push",
  "LANGUAGE": "Sprache",
  "MUSICAL_PREFERENCES": "Vorlieben ",
  "VOTE": "Abstimmung",
  "LIKE": "Gefällt  mir",
  "FAVORITE_SUCCESS": "Der Kanal wurde als Favorit festgelegt",
  "SLEEP_TIMER": "Stell den Alarm ein",
  "DESCRIPTION_GENERAL": "Allgemeine Musik.  Entdecke  die neuesten Lieder!",
  "DESCRIPTION_WORSHIP": "Rumänische Anbetungsmusik. Entdecke dein Lieblingssänger",
  "DESCRIPTION_SERMONS": "Predigten, Podcasts, Shows.  Botschaften für deine Seele!",
  "DESCRIPTION_INTERNATIONAL": "Internationale evangelische Musik.  Ausländische christliche Sänger, die Gott dediziert sind!",
  "DESCRIPTION_INSTRUMENTAL": "Instrumentallieder für die Motivation deines Herzens!",
  "DESCRIPTION_FOLK": "Rumänische Volksmusik und alte christliche Musik."
}